{
  "projects": [
    {
      "name": "Projekt1",
      "id": 1
    },
    {
      "name": "Projekt2",
      "id": 2
    },
    {
      "name": "Projekt3",
      "id": 3
    },
    {
      "name": "TEst21",
      "id": 4
    },
    {
      "name": "tesh",
      "id": 5
    },
    {
      "name": "44553",
      "id": 6
    }
  ],
  "tasks": [
    {
      "name": "Test1",
      "id": 1
    },
    {
      "name": "Test2",
      "id": 2
    },
    {
      "name": "Test3",
      "id": 3
    },
    {
      "name": "waijawdiowa",
      "id": 4
    },
    {
      "name": "113332",
      "id": 5
    }
  ],
  "timelog": [
    {
      "id": 254,
      "taskId": 1,
      "startTime": "2023-05-26T14:50:25.198Z",
      "stopTime": "2023-05-26T14:50:29.753Z"
    },
    {
      "id": 931,
      "taskId": 1,
      "startTime": "2023-05-26T14:55:52.701Z",
      "stopTime": "2023-05-26T14:55:58.255Z"
    },
    {
      "id": 105,
      "taskId": 1,
      "startTime": "2023-05-26T14:56:17.986Z",
      "stopTime": "2023-05-26T14:56:20.345Z"
    },
    {
      "id": 205,
      "taskId": 3,
      "startTime": "2023-05-26T14:56:49.308Z",
      "stopTime": "2023-05-26T14:56:52.565Z"
    },
    {
      "id": 900,
      "taskId": 2,
      "startTime": "2023-05-26T14:59:58.042Z",
      "stopTime": "2023-05-26T15:00:06.490Z"
    },
    {
      "id": 215,
      "taskId": null,
      "startTime": "2023-05-26T15:03:01.478Z",
      "stopTime": "2023-05-26T15:03:03.020Z"
    },
    {
      "id": 286,
      "taskId": 1,
      "startTime": "2023-05-26T15:05:16.219Z",
      "stopTime": "2023-05-26T15:05:19.481Z"
    },
    {
      "id": 936,
      "taskId": 1,
      "startTime": "2023-05-26T23:03:09+02:00",
      "stopTime": "2023-05-26T23:03:12+02:00"
    },
    {
      "id": 134,
      "taskId": 1,
      "startTime": "2023-05-26T23:05:05+02:00",
      "stopTime": "2023-05-26T23:05:07+02:00"
    },
    {
      "id": 536,
      "taskId": 2,
      "startTime": "2023-05-26T23:09:20+02:00",
      "stopTime": "2023-05-26T23:09:23+02:00"
    }
  ],
  "invoice": [
    {
      "name": "TEst1",
      "project": "1",
      "task": [
        {
          "name": "Projekt1",
          "id": 1,
          "time": 3600000
        },
        {
          "name": "Projekt2",
          "id": 1,
          "time": 3600000
        }
      ],
      "timmpris": 1000,
      "createDate": "2023-05-26T08:07:15.731Z",
      "dueDate": "2023-06-26T08:07:15.731Z",
      "status": "Ej betald",
      "id": 2
    },
    {
      "name": "TEst1",
      "project": "1",
      "task": [
        {
          "name": "Test1",
          "id": 1,
          "time": 15730
        }
      ],
      "timmpris": 100,
      "createDate": "2023-05-26T15:14:09.737Z",
      "dueDate": "2023-06-26T15:14:09.737Z",
      "status": "Ej betald",
      "id": 3
    }
  ]
}